jupyter_litchi/__init__.py
jupyter_litchi/_version.py
jupyter_litchi/labextension/build_log.json
jupyter_litchi/labextension/package.json
jupyter_litchi/labextension/schemas/jupyter-litchi/jupyter-litchi.json
jupyter_litchi/labextension/schemas/jupyter-litchi/package.json.orig
jupyter_litchi/labextension/schemas/jupyter-litchi/plugin.json
jupyter_litchi/labextension/static/lib_index_js.ca153a7eac45c8af3c35.js
jupyter_litchi/labextension/static/lib_index_js.ca153a7eac45c8af3c35.js.map
jupyter_litchi/labextension/static/remoteEntry.142f3ffd9e52a3d01028.js
jupyter_litchi/labextension/static/remoteEntry.142f3ffd9e52a3d01028.js.map
jupyter_litchi/labextension/static/style.js
jupyter_litchi/labextension/static/style_index_js.981978d836ccfd963937.js
jupyter_litchi/labextension/static/style_index_js.981978d836ccfd963937.js.map
jupyter_litchi-0.4.5.data/data/share/jupyter/labextensions/jupyter-litchi/build_log.json
jupyter_litchi-0.4.5.data/data/share/jupyter/labextensions/jupyter-litchi/package.json
jupyter_litchi-0.4.5.data/data/share/jupyter/labextensions/jupyter-litchi/schemas/jupyter-litchi/jupyter-litchi.json
jupyter_litchi-0.4.5.data/data/share/jupyter/labextensions/jupyter-litchi/schemas/jupyter-litchi/package.json.orig
jupyter_litchi-0.4.5.data/data/share/jupyter/labextensions/jupyter-litchi/schemas/jupyter-litchi/plugin.json
jupyter_litchi-0.4.5.data/data/share/jupyter/labextensions/jupyter-litchi/static/lib_index_js.ca153a7eac45c8af3c35.js
jupyter_litchi-0.4.5.data/data/share/jupyter/labextensions/jupyter-litchi/static/lib_index_js.ca153a7eac45c8af3c35.js.map
jupyter_litchi-0.4.5.data/data/share/jupyter/labextensions/jupyter-litchi/static/remoteEntry.142f3ffd9e52a3d01028.js
jupyter_litchi-0.4.5.data/data/share/jupyter/labextensions/jupyter-litchi/static/remoteEntry.142f3ffd9e52a3d01028.js.map
jupyter_litchi-0.4.5.data/data/share/jupyter/labextensions/jupyter-litchi/static/style.js
jupyter_litchi-0.4.5.dist-info/METADATA
jupyter_litchi-0.4.5.dist-info/WHEEL
jupyter_litchi-0.4.5.dist-info/licenses/LICENSE
jupyter_litchi-0.4.5.dist-info/RECORD
