Metadata-Version: 2.3
Name: jupyter_litchi
Version: 0.4.5
Summary: A JupyterLab extension.
Project-URL: Homepage, https://github.com/MarchLiu/litchi
Project-URL: Bug Tracker, https://github.com/MarchLiu/litchi/issues
Project-URL: Repository, https://github.com/MarchLiu/litchi.git
Author-email: Mars Liu <mars.liu@outlook.com>
License: BSD 3-Clause License
License-File: LICENSE
Keywords: agent,ai,jupyter,jupyterlab,jupyterlab-extension,llm,ollama,openai
Classifier: Framework :: Jupyter
Classifier: Framework :: Jupyter :: JupyterLab
Classifier: Framework :: Jupyter :: JupyterLab :: 4
Classifier: Framework :: Jupyter :: JupyterLab :: Extensions
Classifier: Framework :: Jupyter :: JupyterLab :: Extensions :: Prebuilt
Classifier: License :: OSI Approved :: BSD License
Classifier: Programming Language :: Python
Classifier: Programming Language :: Python :: 3
Classifier: Programming Language :: Python :: 3.8
Classifier: Programming Language :: Python :: 3.9
Classifier: Programming Language :: Python :: 3.10
Classifier: Programming Language :: Python :: 3.11
Classifier: Programming Language :: Python :: 3.12
Requires-Python: >=3.8
